toolbox/__init__.py
toolbox/utils.py
Jaarvis-0.2.dist-info/LICENSE
Jaarvis-0.2.dist-info/METADATA
Jaarvis-0.2.dist-info/WHEEL
Jaarvis-0.2.dist-info/top_level.txt
Jaarvis-0.2.dist-info/RECORD
